markovclick/__init__.py
markovclick/__version__.py
markovclick/dummy.py
markovclick/models.py
markovclick/preprocessing.py
markovclick/viz.py
markovclick/utils/__init__.py
markovclick/utils/helpers.py
markovclick-0.1.2.dist-info/METADATA
markovclick-0.1.2.dist-info/RECORD
markovclick-0.1.2.dist-info/WHEEL
markovclick-0.1.2.dist-info/top_level.txt
