Metadata-Version: 2.1
Name: markovclick
Version: 0.1.2
Summary: Package for modelling clickstream data using Markov chains
Home-page: https://github.com/ismailuddin/markovclick
Author: Ismail Uddin
License: BSD
Download-URL: https://github.com/ismailuddin/markovclick/tarball/0.1.2
Keywords: markov chain data science machine learning statistics clickstream
Platform: UNKNOWN
Classifier: Development Status :: 3 - Alpha
Classifier: Intended Audience :: Developers
Classifier: Programming Language :: Python :: 3
